mcservercreator/__init__.py
mcservercreator/__main__.py
mcservercreator/constants.py
mcservercreator/utils/__init__.py
mcservercreator/utils/more_options.py
mcservercreator/utils/properties_parser.py
mcservercreator/utils/tools.py
mcservercreator-1.0.2.dist-info/LICENSE
mcservercreator-1.0.2.dist-info/METADATA
mcservercreator-1.0.2.dist-info/WHEEL
mcservercreator-1.0.2.dist-info/top_level.txt
mcservercreator-1.0.2.dist-info/RECORD
