Metadata-Version: 2.1
Name: mcservercreator
Version: 1.0.2
Summary: A tool to help you create and manage minecraft servers easier
Home-page: https://github.com/Ivan-1F/Minecraft-Server-Creator
Author: Ivan1F
License: GPL-3.0
Platform: UNKNOWN
Classifier: Programming Language :: Python :: 3
Classifier: License :: OSI Approved :: GNU General Public License v3 (GPLv3)
Classifier: Operating System :: OS Independent
Requires-Python: >=3.6.0
Requires-Dist: progress
Requires-Dist: inquirer
